artemis_sg/__init__.py
artemis_sg/_version.py
artemis_sg/app_creds.py
artemis_sg/cli.py
artemis_sg/gcloud.py
artemis_sg/img_downloader.py
artemis_sg/isbn.py
artemis_sg/item.py
artemis_sg/items.py
artemis_sg/scraper.py
artemis_sg/slide_generator.py
artemis_sg/spreadsheet.py
artemis_sg/vendor.py
artemis_sg/config/__init__.py
artemis_sg/data/artemis_logo.png
artemis_sg/data/htmlslidedeck_template.html
artemis_sg/data/mailchimp_template.html
artemis_sg-0.6.9.dist-info/METADATA
artemis_sg-0.6.9.dist-info/WHEEL
artemis_sg-0.6.9.dist-info/entry_points.txt
artemis_sg-0.6.9.dist-info/licenses/LICENSE
artemis_sg-0.6.9.dist-info/RECORD
